redact/__init__.py
redact/py.typed
redact/string.py
pyredacter-0.0.8.dist-info/METADATA
pyredacter-0.0.8.dist-info/WHEEL
pyredacter-0.0.8.dist-info/top_level.txt
pyredacter-0.0.8.dist-info/RECORD
