Metadata-Version: 2.4
Name: pyredacter
Version: 0.0.8
Summary: Redact sensitive strings
Author: Scott Walsh
Author-email: scott@invisiblethreat.ca
Maintainer: Scott Walsh
Maintainer-email: scott@invisiblethreat.ca
Project-URL: documentation, https://github.com/invisiblethreat/pyredacter/blob/main/README.md
Project-URL: repository, https://github.com/invisiblethreat/pyredacter
Project-URL: homepage, https://github.com/invisiblethreat/pyredacter
Keywords: redact,password,passwords
Classifier: Development Status :: 4 - Beta
Classifier: Programming Language :: Python
Requires-Python: >=3.7
